tidepy/__init__.py
tidepy/model.py
tidepy/pred.py
tidepy/utils.py
tidepy/data/Gene_Ref.pkl
tidepy/data/model.pkl
tidepy-1.3.8.data/scripts/tidepy
tidepy-1.3.8.dist-info/LICENSE
tidepy-1.3.8.dist-info/METADATA
tidepy-1.3.8.dist-info/WHEEL
tidepy-1.3.8.dist-info/top_level.txt
tidepy-1.3.8.dist-info/RECORD
