Metadata-Version: 2.1
Name: tidepy
Version: 1.3.8
Summary: A computational method to predict immunotherapy response.
Home-page: https://jingxinfu.github.io/TIDEpy
Author: Jingxin Fu
Author-email: jingxinfu.tj@gmail.com
License: UNKNOWN
Keywords: Immunotherapy,ICB Prediction,Biomarkers,Bioinformatics,Computational Biology
Platform: UNKNOWN
Classifier: Programming Language :: Python :: 3
Classifier: License :: OSI Approved :: GNU General Public License v3 or later (GPLv3+)
Classifier: Operating System :: OS Independent
Requires-Python: >=3.4, <4
License-File: LICENSE
Requires-Dist: pandas
Requires-Dist: numpy
